{
  "name": "Enmity",
  "identifier": "enmity",
  "apps": [
    {
      "name": "Enmity",
      "bundleIdentifier": "com.hammerandchisel.discord",
      "developerName": "Enmity Team",
      "subtitle": "The power of addons, all in your hand.",
      "version": "213.0",
      "versionDate": "2024-03-00",
      "versionDescription": "- Updated Discord to 213.0",
      "downloadURL": "https://github.com/enmity-mod/tweak/releases/latest/download/enmity.ipa",
      "localizedDescription": "Add plugins and themes to Discord!",
      "iconURL": "https://enmity-mod.github.io/repo/CydiaIcon@3x.png",
      "tintColor": "6D00FF",
      "size": 76794285,
      "beta": false
    }
  ],
  "userInfo": {}
}
